azcam_expstatus/__init__.py
azcam_expstatus/expstatus.pyw
azcam_expstatus/expstatus.ui
azcam_expstatus/expstatus_ui.py
azcam_expstatus/make_gui.bat
azcam_expstatus-22.4.0.dist-info/entry_points.txt
azcam_expstatus-22.4.0.dist-info/LICENSE
azcam_expstatus-22.4.0.dist-info/WHEEL
azcam_expstatus-22.4.0.dist-info/METADATA
azcam_expstatus-22.4.0.dist-info/RECORD
