Metadata-Version: 2.1
Name: azcam-expstatus
Version: 22.4.0
Summary: An Azcam application which displays exposure progress in a GUI window
Keywords: ccd,imaging,astronomy,sensors
Author: Michael Lesser
Author-email: mlesser@arizona.edu
Requires-Dist: azcam
Requires-Dist: PySide6
Project-URL: Documentation, https://mplesser.github.io/azcam/
Project-URL: Repository, https://github.com/mplesser/azcam-expstatus/
